dtreeviz/__init__.py
dtreeviz/ai_explanation.py
dtreeviz/classifiers.py
dtreeviz/colors.py
dtreeviz/compatibility.py
dtreeviz/interpretation.py
dtreeviz/t3.py
dtreeviz/trees.py
dtreeviz/utils.py
dtreeviz/version.py
dtreeviz/models/__init__.py
dtreeviz/models/lightgbm_decision_tree.py
dtreeviz/models/shadow_decision_tree.py
dtreeviz/models/sklearn_decision_trees.py
dtreeviz/models/spark_decision_tree.py
dtreeviz/models/tensorflow_decision_tree.py
dtreeviz/models/xgb_decision_tree.py
dtreeviz-2.3.1.dist-info/licenses/LICENSE
testing/__init__.py
testing/animate_rtree_bivar_3D.py
testing/cancer.py
testing/gen_feature_space_samples.py
testing/gen_samples.py
testing/iris.py
testing/paper_examples.py
testing/play_ctree.py
testing/play_ctree_bivar.py
testing/play_lightgbm.py
testing/play_rtree.py
testing/play_rtree_bivar_3D.py
testing/play_rtree_bivar_heatmap.py
testing/play_spark.py
testing/testone.py
testing/tf-catvars.py
testing/tf_catvars2.py
testing/tf_catvars3.py
testing/tf_regr_catvars.py
testing/testlib/__init__.py
testing/testlib/models/__init__.py
testing/testlib/models/conftest.py
testing/testlib/models/test_decision_tree_lightgbm_classifier.py
testing/testlib/models/test_decision_tree_spark_classifier.py
testing/testlib/models/test_decision_tree_tensorflow_classifier.py
testing/testlib/models/test_decision_tree_xgb_regressor.py
testing/testlib/models/test_decision_trees_sk_classifier.py
testing/testlib/models/test_decision_trees_sk_pipeline.py
testing/testlib/models/test_decision_trees_xgb_classifier.py
dtreeviz-2.3.1.dist-info/METADATA
dtreeviz-2.3.1.dist-info/WHEEL
dtreeviz-2.3.1.dist-info/top_level.txt
dtreeviz-2.3.1.dist-info/RECORD
