Metadata-Version: 2.4
Name: dtreeviz
Version: 2.3.1
Summary: A Python 3 library for sci-kit learn, XGBoost, LightGBM, Spark, and TensorFlow decision tree visualization
Home-page: https://github.com/parrt/dtreeviz
Author: Terence Parr, Tudor Lapusan, and Prince Grover
Author-email: parrt@antlr.org
License: MIT
Keywords: machine-learning data structures trees visualization
Classifier: License :: OSI Approved :: MIT License
Classifier: Intended Audience :: Developers
Requires-Python: >=3.6
License-File: LICENSE
Requires-Dist: graphviz>=0.9
Requires-Dist: pandas
Requires-Dist: numpy
Requires-Dist: scikit-learn
Requires-Dist: matplotlib
Requires-Dist: colour
Provides-Extra: xgboost
Requires-Dist: xgboost; extra == "xgboost"
Provides-Extra: pyspark
Requires-Dist: pyspark; extra == "pyspark"
Provides-Extra: lightgbm
Requires-Dist: lightgbm; extra == "lightgbm"
Provides-Extra: tensorflow-decision-forests
Requires-Dist: tensorflow_decision_forests; extra == "tensorflow-decision-forests"
Provides-Extra: ai
Requires-Dist: langchain-openai; extra == "ai"
Provides-Extra: all
Requires-Dist: xgboost; extra == "all"
Requires-Dist: pyspark; extra == "all"
Requires-Dist: lightgbm; extra == "all"
Requires-Dist: tensorflow_decision_forests; extra == "all"
Requires-Dist: langchain-openai; extra == "all"
Provides-Extra: dev
Requires-Dist: pytest; extra == "dev"
Dynamic: author
Dynamic: author-email
Dynamic: classifier
Dynamic: description
Dynamic: home-page
Dynamic: keywords
Dynamic: license
Dynamic: license-file
Dynamic: provides-extra
Dynamic: requires-dist
Dynamic: requires-python
Dynamic: summary
